phyphox/__init__.py
phyphox/phyphox.py
phyphox_py-0.0.6.dist-info/licenses/LICENSE
phyphox_py-0.0.6.dist-info/METADATA
phyphox_py-0.0.6.dist-info/WHEEL
phyphox_py-0.0.6.dist-info/top_level.txt
phyphox_py-0.0.6.dist-info/RECORD
