Metadata-Version: 2.4
Name: phyphox-py
Version: 0.0.6
Summary: Python API for phyphox phone application
Author-email: Laurent Berger <laurent.berger@univ-lemans.fr>
License: LICENSE*
Project-URL: Homepage, https://github.com/LaurentBerger/phyphox-py
Project-URL: Issues, https://github.com/LaurentBerger/phyphox-py/issues
Project-URL: documentation, https://phyphox-py.readthedocs.io/en/latest/
Classifier: Programming Language :: Python :: 3
Classifier: Operating System :: OS Independent
Requires-Python: >=3.9
License-File: LICENSE
Dynamic: license-file
